zmaker/__init__.py
zmaker-1.0.4.dist-info/METADATA
zmaker-1.0.4.dist-info/WHEEL
zmaker-1.0.4.dist-info/top_level.txt
zmaker-1.0.4.dist-info/RECORD
