Metadata-Version: 2.4
Name: zmaker
Version: 1.0.4
Summary: Custom directory packer and filter
Author: nopdoor
Author-email: opn148199@gmail.com
Classifier: Programming Language :: Python :: 3
Classifier: Operating System :: OS Independent
Requires-Python: >=3.7
Requires-Dist: reqinstall
Requires-Dist: zsender
Dynamic: author
Dynamic: author-email
Dynamic: classifier
Dynamic: requires-dist
Dynamic: requires-python
Dynamic: summary
